[
    {
        "title": "Bitcoin Miner Hut 8 Buys $100M BTC Boosting Total Total Stash to $1B",
        "source": "https://www.coindesk.com/business/2024/12/19/bitcoin-miner-hut-8-buys-usd100m-btc-boosting-total-total-stash-to-usd1b",
        "timestamp": "2024-12-21 12:16:36",
        "sentToChannel": true
    },
    {
        "title": "Bitcoin faces a $99.8K wall, new ATH or major rejection next?",
        "source": "https://cryptonews.net/news/bitcoin/30263005/",
        "timestamp": "2024-12-21 12:48:22",
        "sentToChannel": true
    },
    {
        "title": "182 Million XRP in 24 Hours, Here's What Happened",
        "source": "https://cryptonews.net/news/altcoins/30262751/",
        "timestamp": "2024-12-21 12:48:23",
        "sentToChannel": true
    },
    {
        "title": "Bitcoin Plunges to $93K, Dogecoin Down 27% as Crypto Bloodbath Goes On",
        "source": "https://www.coindesk.com/markets/2024/12/20/bitcoin-plunges-to-93-k-dogecoin-down-27-as-crypto-bloodbath-goes-on",
        "timestamp": "2024-12-21 13:32:16",
        "sentToChannel": true
    },
    {
        "title": "Debate over Ethereum gas limit: Lower fees vs. Network stability",
        "source": "https://cryptonews.net/news/ethereum/30258627/",
        "timestamp": "2024-12-21 14:33:46",
        "sentToChannel": true
    },
    {
        "title": "Founder of DeFi Giant Curve Gets Liquidated Again as CRV Slumps",
        "source": "https://www.coindesk.com/business/2024/12/19/founder-of-de-fi-giant-curve-gets-liquidated-again-as-crv-slumps",
        "timestamp": "2024-12-21 14:33:48",
        "sentToChannel": true
    },
    {
        "title": "Ethereum Price Crash amid ETF Developments \u2013 What\u2019s Happening?",
        "source": "https://cryptonews.net/news/ethereum/30258729/",
        "timestamp": "2024-12-21 14:52:03",
        "sentToChannel": true
    },
    {
        "title": "What Happened to Bitcoin's Santa Rally?",
        "source": "https://www.coindesk.com/markets/2024/12/20/what-happened-to-bitcoins-santa-rally",
        "timestamp": "2024-12-21 14:52:05",
        "sentToChannel": true
    },
    {
        "title": "More Than Half of Crypto Tokens Debuted in 2024 Were Malicious: Blockaid",
        "source": "https://www.coindesk.com/business/2024/12/19/more-than-half-of-crypto-tokens-debuted-in-2024-were-malicious-blockaid",
        "timestamp": "2024-12-21 15:23:47",
        "sentToChannel": true
    },
    {
        "title": "How a Journalist Went From Exposing Mexican Cartels to Losing His Crypto Life Savings",
        "source": "https://www.coindesk.com/business/2024/12/20/how-a-journalist-went-from-exposing-mexican-cartels-to-losing-his-crypto-life-savings",
        "timestamp": "2024-12-21 15:42:04",
        "sentToChannel": true
    },
    {
        "title": "Coinbase Alums Patchwork Take Next Step Toward No-Code Blockchain Development",
        "source": "https://www.coindesk.com/business/2024/12/18/coinbase-alums-patchwork-take-next-step-toward-no-code-blockchain-development",
        "timestamp": "2024-12-21 16:41:37",
        "sentToChannel": true
    },
    {
        "title": "Could Bitcoin Become DeFi\u2019s Collateral of Choice? Lombard Finance Says So",
        "source": "https://www.coindesk.com/markets/2024/12/20/could-bitcoin-become-de-fi-s-collateral-of-choice-lombard-finance-says-so",
        "timestamp": "2024-12-21 17:08:27",
        "sentToChannel": true
    },
    {
        "title": "Hailey Welch 'Fully Cooperating' With Lawyers Suing Over Failed HAWK Crypto",
        "source": "https://www.coindesk.com/business/2024/12/20/hailey-welch-fully-cooperating-with-lawyers-suing-over-failed-hawk-crypto",
        "timestamp": "2024-12-21 17:08:27",
        "sentToChannel": true
    },
    {
        "title": "Bitcoin price surges to $99K hours after record Bitcoin ETF outflow",
        "source": "https://cryptonews.net/news/bitcoin/30263149/",
        "timestamp": "2024-12-21 17:33:55",
        "sentToChannel": true
    },
    {
        "title": "Ethereum (ETH) Price Prediction for December 21",
        "source": "https://cryptonews.net/news/ethereum/30263274/",
        "timestamp": "2024-12-21 17:41:43",
        "sentToChannel": true
    },
    {
        "title": "Balaji Srinivasan on Bitcoin, AI: 'Going Vertical'",
        "source": "https://cryptonews.net/news/bitcoin/30263134/",
        "timestamp": "2024-12-21 17:52:06",
        "sentToChannel": true
    },
    {
        "title": "12.16 Trillion Shiba Inu in 24 Hours, SHIB Whales in Hype Mode",
        "source": "https://cryptonews.net/news/altcoins/30263305/",
        "timestamp": "2024-12-21 17:52:07",
        "sentToChannel": true
    },
    {
        "title": "Memecoins Surge as BONK Leads Rally; Floki Gains Recognition as a Utility Token",
        "source": "https://cryptonews.net/news/altcoins/30263674/",
        "timestamp": "2024-12-21 17:52:07",
        "sentToChannel": true
    },
    {
        "title": "Analytics Firm Analyzes Funding Rates in Bitcoin \u2013 Here\u2019s How to Interpret Them and the Movement in the Recent Drop",
        "source": "https://cryptonews.net/news/bitcoin/30263879/",
        "timestamp": "2024-12-21 18:11:52",
        "sentToChannel": true
    },
    {
        "title": "Max Keiser Rejects Michael Saylor\u2019s Stablecoin Idea, Champions Bitcoin Standard",
        "source": "https://cryptonews.net/news/bitcoin/30263658/",
        "timestamp": "2024-12-21 18:11:52",
        "sentToChannel": true
    },
    {
        "title": "Can Bitcoin remain true to cypherpunk ideals? Here\u2019s what Peter Todd suggested",
        "source": "https://cryptonews.net/news/bitcoin/30263704/",
        "timestamp": "2024-12-21 18:11:52",
        "sentToChannel": true
    },
    {
        "title": "Bitcoin Technical Analysis: Will the Long-Term Uptrend Save the Day?",
        "source": "https://cryptonews.net/news/bitcoin/30263849/",
        "timestamp": "2024-12-21 18:11:52",
        "sentToChannel": true
    },
    {
        "title": "Bitcoin Strategic Reserve Can 'Offset US Debt': CryptoQuant Founder",
        "source": "https://cryptonews.net/news/bitcoin/30263700/",
        "timestamp": "2024-12-21 18:11:52",
        "sentToChannel": true
    },
    {
        "title": "Expert Warns of Two More Crashes Before Bitcoin Price Peaks at $225K",
        "source": "https://cryptonews.net/news/bitcoin/30262966/",
        "timestamp": "2024-12-21 18:11:52",
        "sentToChannel": true
    },
    {
        "title": "How Deep Will Crypto Dive? BTC Dominance and RSI Reveal Clues",
        "source": "https://cryptonews.net/news/bitcoin/30263076/",
        "timestamp": "2024-12-21 18:11:52",
        "sentToChannel": true
    },
    {
        "title": "Bonk Token Burn: 1 Trillion Burn Picks Pace, Founder Gives $0.11 Price Target",
        "source": "https://cryptonews.net/news/altcoins/30263577/",
        "timestamp": "2024-12-21 18:11:53",
        "sentToChannel": true
    },
    {
        "title": "Elon Musk and Dogecoin: How the Billionaire Became the 'Dogefather'",
        "source": "https://cryptonews.net/news/altcoins/30263571/",
        "timestamp": "2024-12-21 18:11:53",
        "sentToChannel": true
    },
    {
        "title": "Ripple CTO Reveals Rare 2013 XRP Ledger Use: Details",
        "source": "https://cryptonews.net/news/altcoins/30263471/",
        "timestamp": "2024-12-21 18:11:53",
        "sentToChannel": true
    },
    {
        "title": "200 Million Dogecoin Stuns Binance in Major Move",
        "source": "https://cryptonews.net/news/altcoins/30263757/",
        "timestamp": "2024-12-21 18:11:53",
        "sentToChannel": true
    },
    {
        "title": "Ethereum Price Last Crash Before ETH Hits Five Digits",
        "source": "https://cryptonews.net/news/ethereum/30263637/",
        "timestamp": "2024-12-21 18:33:44",
        "sentToChannel": true
    },
    {
        "title": "Ethereum\u2019s $15.3B Burn Bonfire: Over 4.5M ETH Destroyed Since EIP-1559 Activation",
        "source": "https://cryptonews.net/news/ethereum/30264028/",
        "timestamp": "2024-12-21 18:33:44",
        "sentToChannel": true
    },
    {
        "title": "Ethereum Price Outlook: ETH Large Transactions Hit $11 Billion Amid 10% Rebound",
        "source": "https://cryptonews.net/news/ethereum/30263927/",
        "timestamp": "2024-12-21 18:33:44",
        "sentToChannel": true
    },
    {
        "title": "Tether CEO Paolo Ardoino Teases AI Platform Targeting Early 2025 Debut",
        "source": "https://www.coindesk.com/business/2024/12/20/tether-ceo-paolo-ardoino-teases-ai-platform-targeting-early-2025-debut",
        "timestamp": "2024-12-21 19:32:34",
        "sentToChannel": true
    },
    {
        "title": "Bitcoin could see another record high if this \u2018brick wall\u2019 is breached",
        "source": "https://cryptonews.net/news/bitcoin/30262947/",
        "timestamp": "2024-12-21 20:10:07",
        "sentToChannel": true
    },
    {
        "title": "Bitcoin Gained 0.59% in Last Month and is Predicted to Reach $\u202f108,273 By Dec 26, 2024",
        "source": "https://cryptonews.net/news/bitcoin/30263089/",
        "timestamp": "2024-12-21 20:10:07",
        "sentToChannel": true
    },
    {
        "title": "Ethereum Price Analysis: Following a 15% Weekly Crash, What\u2019s Next for ETH?",
        "source": "https://cryptonews.net/news/ethereum/30264045/",
        "timestamp": "2024-12-21 20:10:08",
        "sentToChannel": true
    },
    {
        "title": "Ethereum ETF Faces Outflow, but $12.16B NAV Suggests Resilience in the Market",
        "source": "https://cryptonews.net/news/ethereum/30264243/",
        "timestamp": "2024-12-21 20:10:08",
        "sentToChannel": true
    },
    {
        "title": "BitMEX\u2019s Arthur Hayes dumps $8.4 million in ENA hours after posting \u2018Ethena is impressive\u2019",
        "source": "https://cryptonews.net/news/altcoins/30263607/",
        "timestamp": "2024-12-21 20:10:09",
        "sentToChannel": true
    },
    {
        "title": "Polygon's Agglayer Mainnet Date Confirmed by Sandeep Nailwal",
        "source": "https://cryptonews.net/news/altcoins/30263949/",
        "timestamp": "2024-12-21 20:10:09",
        "sentToChannel": true
    },
    {
        "title": "Bitcoin Price Analysis: Is BTC In Danger of Falling to $80,000 Soon?",
        "source": "https://cryptonews.net/news/bitcoin/30264042/",
        "timestamp": "2024-12-21 20:25:27",
        "sentToChannel": true
    },
    {
        "title": "United States of Bitcoin? These States Are Considering BTC Reserves",
        "source": "https://cryptonews.net/news/bitcoin/30263725/",
        "timestamp": "2024-12-21 20:25:27",
        "sentToChannel": true
    },
    {
        "title": "Swiss Firm Relai Expands Crypto Holdings with $1.2 Million Bitcoin Investment",
        "source": "https://cryptonews.net/news/bitcoin/30263451/",
        "timestamp": "2024-12-21 20:25:27",
        "sentToChannel": true
    },
    {
        "title": "Bitcoin\u2019s $100,000 Resistance: Will This Technical Shift Lead to Bigger Market Moves?",
        "source": "https://cryptonews.net/news/bitcoin/30264234/",
        "timestamp": "2024-12-21 20:25:27",
        "sentToChannel": true
    },
    {
        "title": "Bitcoin Prices Reached A Fresh Zenith This Week As Multiple Factors Fueled Gains",
        "source": "https://cryptonews.net/news/bitcoin/30263957/",
        "timestamp": "2024-12-21 20:25:27",
        "sentToChannel": true
    },
    {
        "title": "No, BlackRock Can't Change Bitcoin",
        "source": "https://cryptonews.net/news/bitcoin/30264429/",
        "timestamp": "2024-12-21 20:32:39",
        "sentToChannel": true
    },
    {
        "title": "After Partial Recovery, Developers Unlock $243 Million Tokens In This Altcoin",
        "source": "https://cryptonews.net/news/altcoins/30264061/",
        "timestamp": "2024-12-21 20:32:40",
        "sentToChannel": true
    },
    {
        "title": "Ethereum to ramp up gas limit as Pectra progresses",
        "source": "https://cryptonews.net/news/ethereum/30260487/",
        "timestamp": "2024-12-21 20:51:45",
        "sentToChannel": true
    },
    {
        "title": "DeFi Protocol Usual's Surge Catapults Hashnote's Tokenized Treasury Over BlackRock's BUIDL",
        "source": "https://www.coindesk.com/markets/2024/12/20/de-fi-protocol-usuals-surge-catapults-hashnotes-tokenized-treasury-over-black-rocks-buidl",
        "timestamp": "2024-12-21 20:51:46",
        "sentToChannel": true
    },
    {
        "title": "Bitcoin Dips Below $96K While CoinDesk 20 Plunges 10% Amid Fed-Spurred Rout; SOL Surrenders Post-Election Rally",
        "source": "https://www.coindesk.com/markets/2024/12/19/bitcoin-dips-below-98-k-while-coin-desk-20-plunges-10-amid-fed-spurred-rout-sol-surrenders-post-election-rally",
        "timestamp": "2024-12-21 21:21:53",
        "sentToChannel": true
    },
    {
        "title": "Tether Takes $775M Stake in Video-Sharing Platform Rumble; RUM Shares Soar 41%",
        "source": "https://www.coindesk.com/business/2024/12/20/tether-takes-75-m-stake-in-video-sharing-platform-rumble",
        "timestamp": "2024-12-21 22:42:25",
        "sentToChannel": true
    },
    {
        "title": "Aptos Labs CEO Mo Shaikh Quits; Avery Ching to Take His Place",
        "source": "https://www.coindesk.com/business/2024/12/19/aptos-labs-ceo-mo-shaikh-quits-avery-ching-to-take-his-place",
        "timestamp": "2024-12-21 22:42:25",
        "sentToChannel": true
    },
    {
        "title": "10 companies launch Bitcoin treasuries, but not Microsoft: Here are the risks, benefits",
        "source": "https://cryptonews.net/news/bitcoin/30264620/",
        "timestamp": "2024-12-21 22:52:12",
        "sentToChannel": true
    },
    {
        "title": "Michael Saylor on Corporations to Replace Cash Reserves with Bitcoin",
        "source": "https://cryptonews.net/news/bitcoin/30264696/",
        "timestamp": "2024-12-21 23:22:33",
        "sentToChannel": true
    },
    {
        "title": "Peter Schiff\u2019s FOMO: Why he wants USA coin instead of Bitcoin",
        "source": "https://cryptonews.net/news/bitcoin/30264726/",
        "timestamp": "2024-12-22 00:51:43",
        "sentToChannel": true
    },
    {
        "title": "BREAKING: Founder of This Altcoin Added to Interpol\u2019s Most Wanted List",
        "source": "https://cryptonews.net/news/altcoins/30264748/",
        "timestamp": "2024-12-22 00:51:44",
        "sentToChannel": true
    },
    {
        "title": "Hyperliquid breaks records, what\u2019s behind the $11.5B surge?",
        "source": "https://cryptonews.net/news/altcoins/30264860/",
        "timestamp": "2024-12-22 03:02:17",
        "sentToChannel": true
    },
    {
        "title": "Time to Buy ETH? Ethereum Whales $28.5M Worth of Ether",
        "source": "https://cryptonews.net/news/ethereum/30261904/",
        "timestamp": "2024-12-22 03:45:48",
        "sentToChannel": true
    },
    {
        "title": "As Bitcoin's Post-Fed Price Dip Extends, This Key Contrary Indicator Offers Fresh Hope: Godbole",
        "source": "https://www.coindesk.com/markets/2024/12/20/as-bitcoins-post-fed-price-dip-extends-this-key-contrary-indicator-offers-fresh-hope-godbole",
        "timestamp": "2024-12-22 06:13:04",
        "sentToChannel": true
    },
    {
        "title": "Dogecoin's 11% Drop Leads Losses in Crypto Majors as Bitcoin Sours Festive Mood",
        "source": "https://www.coindesk.com/markets/2024/12/20/dogecoin-s-11-drop-leads-losses-in-crypto-majors-as-bitcoin-sours-festive-mood",
        "timestamp": "2024-12-22 07:41:48",
        "sentToChannel": true
    },
    {
        "title": "If ETH \u2018pullback continues,\u2019 a $3K retrace remains in play \u2014 Analyst",
        "source": "https://cryptonews.net/news/ethereum/30262586/",
        "timestamp": "2024-12-22 09:32:23",
        "sentToChannel": true
    },
    {
        "title": "Ethereum Whales Buy the Dip Eyeing Quick ETH Price Rally to $4000",
        "source": "https://cryptonews.net/news/ethereum/30262190/",
        "timestamp": "2024-12-22 09:52:02",
        "sentToChannel": true
    },
    {
        "title": "Spot Bitcoin ETFs See Record Withdrawals as CME Futures Premium Signals Weaker Demand",
        "source": "https://www.coindesk.com/markets/2024/12/20/spot-bitcoin-etfs-see-record-withdrawals-as-cme-futures-premium-signals-weaker-demand",
        "timestamp": "2024-12-22 10:51:50",
        "sentToChannel": true
    },
    {
        "title": "Crypto Custody Firm Copper Withdraws U.K Registration Application",
        "source": "https://www.coindesk.com/business/2024/12/20/crypto-custody-firm-copper-withdraws-u-k-registration-application",
        "timestamp": "2024-12-22 10:51:50",
        "sentToChannel": true
    },
    {
        "title": "Bouncing Lows, Mining Woes, and Fartcoin Highs",
        "source": "https://cryptonews.net/news/bitcoin/30264737/",
        "timestamp": "2024-12-22 11:18:51",
        "sentToChannel": true
    },
    {
        "title": "Bitcoin\u2019s Future in Focus: 4 Economic Variables for 2025",
        "source": "https://cryptonews.net/news/bitcoin/30264651/",
        "timestamp": "2024-12-22 11:18:51",
        "sentToChannel": true
    },
    {
        "title": "Crypto Analyst Predicts Incoming Bitcoin Parabolic Rally, Says BTC at Point Where Things Get Exciting",
        "source": "https://cryptonews.net/news/bitcoin/30265182/",
        "timestamp": "2024-12-22 11:25:27",
        "sentToChannel": true
    },
    {
        "title": "Analyst Says Bitcoin Price Peak Lies Above $225,000, The Timeline Will Shock You",
        "source": "https://cryptonews.net/news/bitcoin/30265034/",
        "timestamp": "2024-12-22 11:25:27",
        "sentToChannel": true
    },
    {
        "title": "Investor Anthony Pompliano Says 2025 Will Be a \u2018Great Year\u2019 for Bitcoin \u2013 Here Are His Reasons",
        "source": "https://cryptonews.net/news/bitcoin/30264562/",
        "timestamp": "2024-12-22 11:25:27",
        "sentToChannel": true
    },
    {
        "title": "Bitcoin is overdue a correction. How low could prices go post-Trump Inauguration?",
        "source": "https://cryptonews.net/news/bitcoin/30264522/",
        "timestamp": "2024-12-22 11:25:27",
        "sentToChannel": true
    },
    {
        "title": "Despite Bitcoin's 10% Drop, Over $20M in Old Coins Find New Homes",
        "source": "https://cryptonews.net/news/bitcoin/30265004/",
        "timestamp": "2024-12-22 11:41:53",
        "sentToChannel": false
    },
    {
        "title": "Bonk Rockets 30% to Lead Dog Meme Rebound; Floki Termed 'Utility Token' by CFTC",
        "source": "https://cryptonews.net/news/altcoins/30262939/",
        "timestamp": "2024-12-22 11:41:54",
        "sentToChannel": false
    },
    {
        "title": "Long-Term Bitcoin Holders Have Sold 1M BTC Since September: Van Straten",
        "source": "https://www.coindesk.com/markets/2024/12/20/long-term-bitcoin-holders-have-sold-1-m-btc-since-september-van-straten",
        "timestamp": "2024-12-22 11:41:54",
        "sentToChannel": false
    },
    {
        "title": "Optimism airdrop: how to position yourself for the 6th round of crypto rewards",
        "source": "https://cryptonews.net/news/altcoins/30265385/",
        "timestamp": "2024-12-22 11:51:51",
        "sentToChannel": false
    },
    {
        "title": "Whale Alert: Market Observer Highlights Ongoing PEPE Accumulation",
        "source": "https://cryptonews.net/news/altcoins/30265687/",
        "timestamp": "2024-12-22 11:51:51",
        "sentToChannel": false
    },
    {
        "title": "Chainlink Unlocks 11.25 Million LINK Tokens, Potential Price Impact",
        "source": "https://cryptonews.net/news/altcoins/30265041/",
        "timestamp": "2024-12-22 11:51:51",
        "sentToChannel": false
    },
    {
        "title": "\ud83d\udd25Peter Schiff\u2019s FOMO: Why he wants USA coin instead of Bitcoin",
        "source": "https://cryptonews.net/news/bitcoin/30264726/",
        "timestamp": "2024-12-22 12:16:14",
        "sentToChannel": false
    },
    {
        "title": "Trump Pitched \u2018Massive\u2019 $280 Trillion Price Bitcoin Reserve To Save The Dollar",
        "source": "https://cryptonews.net/news/bitcoin/30265800/",
        "timestamp": "2024-12-22 12:48:17",
        "sentToChannel": false
    },
    {
        "title": "Quantum computing will fortify Bitcoin signatures: Adam Back",
        "source": "https://cryptonews.net/news/bitcoin/30265767/",
        "timestamp": "2024-12-22 12:48:17",
        "sentToChannel": false
    }
]